README.md
nufictl/__init__.py
nufictl/config.yaml
nufictl/config_manager.py
nufictl/help_texts.py
nufictl/model.py
nufictl/nufictl.py
nufictl/stream_tester.py
nufictl/utils.py
nufictl/yoga.mp4
nufictl-1.0.4.dist-info/METADATA
nufictl-1.0.4.dist-info/WHEEL
nufictl-1.0.4.dist-info/entry_points.txt
nufictl-1.0.4.dist-info/RECORD
