Metadata-Version: 2.1
Name: nufictl
Version: 1.0.4
Summary: Nufictl is a command-line tool for managing CRD Npu Deployments.
Author: dudaji-inc
Author-email: dudajiinc2018@gmail.com
Requires-Python: >=3.8,<4.0
Classifier: Programming Language :: Python :: 3
Classifier: Programming Language :: Python :: 3.8
Classifier: Programming Language :: Python :: 3.9
Classifier: Programming Language :: Python :: 3.10
Classifier: Programming Language :: Python :: 3.11
Classifier: Programming Language :: Python :: 3.12
Requires-Dist: fire (>=0.6.0,<0.7.0)
Requires-Dist: pillow (>=10.4.0,<11.0.0)
Requires-Dist: pydantic (>=2.8.2,<3.0.0)
Requires-Dist: pyyaml (>=6.0.1,<7.0.0)
Requires-Dist: requests (>=2.32.3,<3.0.0)
Requires-Dist: setuptools (>=72.1.0,<73.0.0)
Requires-Dist: tabulate (>=0.9.0,<0.10.0)
Requires-Dist: toml (>=0.10.2,<0.11.0)
Requires-Dist: tqdm (>=4.66.5,<5.0.0)
Requires-Dist: websockets (>=12.0,<13.0)
